cw_test/__init__.py
cw_test/__main__.py
cw_test-1.0.8.dist-info/METADATA
cw_test-1.0.8.dist-info/WHEEL
cw_test-1.0.8.dist-info/RECORD
