Metadata-Version: 2.4
Name: cw_test
Version: 1.0.8
Summary: A library for programming animations with Manim in Google Colab.
Project-URL: Homepage, https://example.com
Project-URL: Repository, https://github.com/me/spam.git
Author-email: CuriousWalk <CWalk@example.com>
License: MIT License
Keywords: Science Animation
Classifier: Intended Audience :: Education
Classifier: Intended Audience :: Science/Research
Classifier: License :: OSI Approved :: MIT License
Classifier: Natural Language :: English
Classifier: Operating System :: OS Independent
Classifier: Programming Language :: Python
Classifier: Topic :: Education
Classifier: Topic :: Multimedia
Classifier: Topic :: Scientific/Engineering
